mas_apip/__init__.py
mas_apip/apip.py
ngetes_bikin_package-0.0.1.dist-info/LICENSE
ngetes_bikin_package-0.0.1.dist-info/METADATA
ngetes_bikin_package-0.0.1.dist-info/WHEEL
ngetes_bikin_package-0.0.1.dist-info/top_level.txt
ngetes_bikin_package-0.0.1.dist-info/RECORD
