Metadata-Version: 2.1
Name: ngetes-bikin-package
Version: 0.0.1
Summary: Coba-coba setelah sekian lama tidak membuat package
Author-email: Mas mas ganteng <tampan@example.com>
License: Copyright (c) 2018 The Python Packaging Authority        
Classifier: Programming Language :: Python :: 3
Classifier: License :: OSI Approved :: MIT License
Classifier: Operating System :: OS Independent
Requires-Python: >=3.8
License-File: LICENSE
